jwtdown_fastapi/__init__.py
jwtdown_fastapi/authentication.py
jwtdown_fastapi-0.6.0.dist-info/LICENSE
jwtdown_fastapi-0.6.0.dist-info/METADATA
jwtdown_fastapi-0.6.0.dist-info/WHEEL
jwtdown_fastapi-0.6.0.dist-info/RECORD
