Metadata-Version: 2.1
Name: jwtdown-fastapi
Version: 0.6.0
Summary: An easy-to-use authentication library for FastAPI.
Home-page: https://gitlab.com/galvanize-inc/foss/jwtdown-fastapi
License: MIT
Keywords: fastapi,authentication
Author: Galvanize, Inc.
Author-email: foss@galvanize.com
Maintainer: Daniel Billotte
Maintainer-email: daniel.billotte@galvanize.com
Requires-Python: >=3.11,<4.0
Classifier: License :: OSI Approved :: MIT License
Classifier: Programming Language :: Python :: 3
Classifier: Programming Language :: Python :: 3.11
Classifier: Programming Language :: Python :: 3.12
Requires-Dist: fastapi (>=0.104.1,<=0.109.0)
Requires-Dist: passlib[bcrypt] (>=1.7.4,<2.0.0)
Requires-Dist: python-jose[cryptography] (>=3.3.0,<4.0.0)
Requires-Dist: python-multipart (>=0.0.6,<0.0.7)
Project-URL: Documentation, https://jwtdown-fastapi.readthedocs.io/
Project-URL: Repository, https://gitlab.com/galvanize-inc/foss/jwtdown-fastapi
